static_models/__init__.py
static_models/apps.py
static_models/response.py
static_models/settings.py
static_models/test.repl
static_models/utils.py
static_models/view_generator.py
static_models/views.py
static_models/management/commands/viewstaticmerge.py
static_models/tests/test_generate.py
django_static_models-1.1.1.dist-info/LICENSE
django_static_models-1.1.1.dist-info/WHEEL
django_static_models-1.1.1.dist-info/METADATA
django_static_models-1.1.1.dist-info/RECORD
