Metadata-Version: 2.1
Name: django-static-models
Version: 1.1.1
Summary: Generate static pages from views
Home-page: https://github.com/rcrowther/django-static_models
Author: robert crowther
Author-email: rw.crowther@gmail.com
Classifier: Operating System :: OS Independent
Classifier: License :: OSI Approved :: BSD License
Classifier: Programming Language :: Python :: 3
Classifier: Framework :: Django
